LICENSE.txt
MANIFEST.in
README.md
requirements.txt
setup.py
gauth/__init__.py
gauth/main.py
gauth.egg-info/PKG-INFO
gauth.egg-info/SOURCES.txt
gauth.egg-info/dependency_links.txt
gauth.egg-info/entry_points.txt
gauth.egg-info/requires.txt
gauth.egg-info/top_level.txt
gauth/extract/__init__.py
gauth/extract/extract_otp_secrets.py
gauth/extract/protobuf_generated_python/__init__.py
gauth/extract/protobuf_generated_python/google_auth_pb2.py