Metadata-Version: 2.1
Name: gauth
Version: 1.0.8
Summary: Tool to help migrate Google Authenticator from phone to desktop
Home-page: https://github.com/damonYuan/gauth
Author: Damon Yuan
Author-email: damon.yuan.dev@gmail.com
License: MIT
Classifier: Programming Language :: Python :: 3
Classifier: License :: OSI Approved :: MIT License
Requires-Python: >=3.6
License-File: LICENSE.txt
